wsp_balsa/__init__.py
wsp_balsa/_version.py
wsp_balsa/logging.py
wsp_balsa/routines/__init__.py
wsp_balsa/routines/best_intermediates.py
wsp_balsa/routines/general.py
wsp_balsa/routines/matrices.py
wsp_balsa/routines/modelling.py
wsp_balsa/routines/plotting.py
wsp_balsa/routines/time.py
wsp_balsa/routines/io/__init__.py
wsp_balsa/routines/io/agent.py
wsp_balsa/routines/io/common.py
wsp_balsa/routines/io/fortran.py
wsp_balsa/routines/io/inro.py
wsp_balsa/routines/io/nwp.py
wsp_balsa/routines/io/omx.py
wsp_balsa-2.1.7.dist-info/licenses/LICENSE
wsp_balsa-2.1.7.dist-info/METADATA
wsp_balsa-2.1.7.dist-info/WHEEL
wsp_balsa-2.1.7.dist-info/top_level.txt
wsp_balsa-2.1.7.dist-info/RECORD
