Metadata-Version: 2.4
Name: wsp-balsa
Version: 2.1.7
Summary: Python tools for travel demand forecasting applications and analyses
Author-email: Brian Cheung <brian.cheung@wsp.com>
Project-URL: Homepage, https://github.com/wsp-sag/balsa
Project-URL: Issues, https://github.com/wsp-sag/balsa/issues
Classifier: Development Status :: 4 - Beta
Classifier: License :: OSI Approved :: BSD License
Classifier: Operating System :: OS Independent
Classifier: Programming Language :: Python :: 3
Requires-Python: <3.14,>=3.7
License-File: LICENSE
Requires-Dist: pandas>=0.24
Requires-Dist: numpy>=1.21
Requires-Dist: numexpr>=2.6
Provides-Extra: plotting
Requires-Dist: matplotlib>=3.0; extra == "plotting"
Provides-Extra: matrices
Requires-Dist: numba>=0.35; extra == "matrices"
Requires-Dist: openmatrix; extra == "matrices"
Provides-Extra: tables
Requires-Dist: h5py<4,>=3.14.0; extra == "tables"
Dynamic: license-file
